Workbook

Sheet Cover
B2: HBC Concierge — Profitability Model
B3: Hometown Builders Club | Management-fee model | Vendor invoices pass through at cost
B5: TIER ECONOMICS (per customer, annual)
B6: Metric | C6: Essentials | D6: Comfort | E6: Premier | F6: Snowbird
B7: Monthly fee | C7: ='6. Assumptions'!$C$6 -> 199 | D7: ='6. Assumptions'!$C$7 -> 350 | E7: ='6. Assumptions'!$C$8 -> 550 | F7: ='6. Assumptions'!$C$9 -> 399
B8: Months billed | C8: ='1. Tier Economics'!C8 -> 12 | D8: ='1. Tier Economics'!D8 -> 12 | E8: ='1. Tier Economics'!E8 -> 12 | F8: ='1. Tier Economics'!F8 -> 6
B9: Annual mgmt fee revenue | C9: ='1. Tier Economics'!C9 -> 2388 | D9: ='1. Tier Economics'!D9 -> 4200 | E9: ='1. Tier Economics'!E9 -> 6600 | F9: ='1. Tier Economics'!F9 -> 2394
B10: Annual add-on revenue | C10: ='1. Tier Economics'!C10 -> 180 | D10: ='1. Tier Economics'!D10 -> 360 | E10: ='1. Tier Economics'!E10 -> 600 | F10: ='1. Tier Economics'!F10 -> 120
B11: TOTAL HBC ANNUAL REVENUE | C11: ='1. Tier Economics'!C13 -> 2568 | D11: ='1. Tier Economics'!D13 -> 4560 | E11: ='1. Tier Economics'!E13 -> 7200 | F11: ='1. Tier Economics'!F13 -> 2514
B12: HBC direct cost | C12: ='1. Tier Economics'!C22 -> 696 | D12: ='1. Tier Economics'!D22 -> 1236 | E12: ='1. Tier Economics'!E22 -> 1956 | F12: ='1. Tier Economics'!F22 -> 888
B13: Annual contribution | C13: ='1. Tier Economics'!C24 -> 1872 | D13: ='1. Tier Economics'!D24 -> 3324 | E13: ='1. Tier Economics'!E24 -> 5244 | F13: ='1. Tier Economics'!F24 -> 1626
B14: Contribution margin % | C14: ='1. Tier Economics'!C25 -> 0.72897196 | D14: ='1. Tier Economics'!D25 -> 0.72894737 | E14: ='1. Tier Economics'!E25 -> 0.72833333 | F14: ='1. Tier Economics'!F25 -> 0.64677804
B15: Customer LTV (after CAC) | C15: ='1. Tier Economics'!C28 -> 10050 | D15: ='1. Tier Economics'!D28 -> 18116.667 | E15: ='1. Tier Economics'!E28 -> 28783.333 | F15: ='1. Tier Economics'!F28 -> 8683.3333
B16: LTV : CAC ratio | C16: ='1. Tier Economics'!C29 -> 29.714286 | D16: ='1. Tier Economics'!D29 -> 52.761905 | E16: ='1. Tier Economics'!E29 -> 83.238095 | F16: ='1. Tier Economics'!F29 -> 25.809524
B19: BUSINESS SCENARIOS (year 1)
B20: Metric | C20: Conservative | D20: Base | E20: Stretch
B21: Total customers (yr 1 end) | C21: ='3. Scenario Analysis'!C7 -> 30 | D21: ='3. Scenario Analysis'!D7 -> 60 | E21: ='3. Scenario Analysis'!E7 -> 100
B22: Total HBC annual revenue | C22: ='3. Scenario Analysis'!C27 -> 115731 | D22: ='3. Scenario Analysis'!D27 -> 251334 | E22: ='3. Scenario Analysis'!E27 -> 441780
B23: Annual contribution (per-cust subtotal) | C23: ='3. Scenario Analysis'!C34 -> 84033 | D23: ='3. Scenario Analysis'!D34 -> 182538 | E23: ='3. Scenario Analysis'!E34 -> 319860
B24: Net contribution (yr 1, after fixed) | C24: ='3. Scenario Analysis'!C41 -> 25533 | D24: ='3. Scenario Analysis'!D41 -> 68538 | E24: ='3. Scenario Analysis'!E41 -> 191860
B27: 36-MONTH FORECAST (Base scenario)
B28: Year 1 ending customers | C28: ='5. 36-Month Forecast'!C25 -> 51.5
B29: Year 2 ending customers | C29: ='5. 36-Month Forecast'!C26 -> 124.3
B30: Year 3 ending customers | C30: ='5. 36-Month Forecast'!C27 -> 203.8
B31: Year 1 net contribution | C31: ='5. 36-Month Forecast'!C29 -> 8816.2
B32: Year 2 net contribution | C32: ='5. 36-Month Forecast'!C30 -> 171161
B33: Year 3 net contribution | C33: ='5. 36-Month Forecast'!C31 -> 415884.8
B34: 3-year cumulative contribution | C34: ='5. 36-Month Forecast'!C33 -> 595862
B37: Tabs: 1) Tier Economics 2) Vendor Pass-Through Reference 3) Scenarios 4) Sensitivity 5) 36-Month Forecast 6) Assumptions

Sheet 1. Tier Economics
B2: Per-Customer Tier Economics
B3: Management-fee model. Vendor invoices pass through at cost. HBC earns the management fee + add-on margin.
B5: Line item | C5: Essentials | D5: Comfort | E5: Premier | F5: Snowbird | G5: Notes
B6: REVENUE
B7: Monthly management fee | C7: ='6. Assumptions'!$C$6 -> 199 | D7: ='6. Assumptions'!$C$7 -> 350 | E7: ='6. Assumptions'!$C$8 -> 550 | F7: ='6. Assumptions'!$C$9 -> 399 | G7: Pulled from Assumptions
B8: Months billed/yr | C8: 12 | D8: 12 | E8: 12 | F8: 6 | G8: Snowbird is Nov-Apr only
B9: Annual management fee revenue | C9: =C7*C8 -> 2388 | D9: =D7*D8 -> 4200 | E9: =E7*E8 -> 6600 | F9: =F7*F8 -> 2394
B10: Add-on / project mgmt revenue (annual) | C10: ='6. Assumptions'!$C$21*12*0.3 -> 180 | D10: ='6. Assumptions'!$C$21*12*0.6 -> 360 | E10: ='6. Assumptions'!$C$21*12*1 -> 600 | F10: ='6. Assumptions'!$C$21*6*0.4 -> 120 | G10: Penetration scales by tier
B11: Vendor pass-through volume (annual, info only) | C11: 2400 | D11: 4800 | E11: 8500 | F11: 1800 | G11: Pass-through is revenue-neutral (cost+0%)
B12: Vendor management fee (if charged) | C12: =C11*'6. Assumptions'!$C$18 -> 0 | D12: =D11*'6. Assumptions'!$C$18 -> 0 | E12: =E11*'6. Assumptions'!$C$18 -> 0 | F12: =F11*'6. Assumptions'!$C$18 -> 0
B13: TOTAL ANNUAL HBC REVENUE | C13: =C9+C10+C12 -> 2568 | D13: =D9+D10+D12 -> 4560 | E13: =E9+E10+E12 -> 7200 | F13: =F9+F10+F12 -> 2514
B15: HBC DIRECT COST (excluding pass-through)
B16: Adam's coordination time hrs/yr per cust | C16: 6 | D16: 12 | E16: 20 | F16: 10 | G16: Year 1 lean launch (Adam-only)
B17: Adam's effective rate $/hr | C17: 75 | D17: =$C$17 -> 75 | E17: =$C$17 -> 75 | F17: =$C$17 -> 75 | G17: Owner opportunity-cost rate
B18: Annual coordination cost | C18: =C16*C17 -> 450 | D18: =D16*D17 -> 900 | E18: =E16*E17 -> 1500 | F18: =F16*F17 -> 750
B19: Software / client portal /yr | C19: ='6. Assumptions'!$C$16*C8 -> 96 | D19: ='6. Assumptions'!$C$16*D8 -> 96 | E19: ='6. Assumptions'!$C$16*E8 -> 96 | F19: ='6. Assumptions'!$C$16*F8 -> 48
B20: Insurance + bond /yr | C20: ='6. Assumptions'!$C$17*C8 -> 60 | D20: ='6. Assumptions'!$C$17*D8 -> 60 | E20: ='6. Assumptions'!$C$17*E8 -> 60 | F20: ='6. Assumptions'!$C$17*F8 -> 30
B21: Add-on cost (1 - margin) | C21: =C10*(1-'6. Assumptions'!$C$22) -> 90 | D21: =D10*(1-'6. Assumptions'!$C$22) -> 180 | E21: =E10*(1-'6. Assumptions'!$C$22) -> 300 | F21: =F10*(1-'6. Assumptions'!$C$22) -> 60
B22: TOTAL HBC DIRECT COST | C22: =SUM(C18:C21) -> 696 | D22: =SUM(D18:D21) -> 1236 | E22: =SUM(E18:E21) -> 1956 | F22: =SUM(F18:F21) -> 888
B24: CONTRIBUTION MARGIN (annual) | C24: =C13-C22 -> 1872 | D24: =D13-D22 -> 3324 | E24: =E13-E22 -> 5244 | F24: =F13-F22 -> 1626
B25: Contribution margin % | C25: =IFERROR(C24/C13,0) -> 0.72897196 | D25: =IFERROR(D24/D13,0) -> 0.72894737 | E25: =IFERROR(E24/E13,0) -> 0.72833333 | F25: =IFERROR(F24/F13,0) -> 0.64677804
B27: Avg customer lifetime (yrs) | C27: =1/'6. Assumptions'!$C$20 -> 5.5555556 | D27: =1/'6. Assumptions'!$C$20 -> 5.5555556 | E27: =1/'6. Assumptions'!$C$20 -> 5.5555556 | F27: =1/'6. Assumptions'!$C$20 -> 5.5555556
B28: Customer LTV (after CAC) | C28: =C24*C27-'6. Assumptions'!$C$19 -> 10050 | D28: =D24*D27-'6. Assumptions'!$C$19 -> 18116.667 | E28: =E24*E27-'6. Assumptions'!$C$19 -> 28783.333 | F28: =F24*F27-'6. Assumptions'!$C$19 -> 8683.3333
B29: LTV : CAC ratio | C29: =IFERROR((C24*C27)/'6. Assumptions'!$C$19,0) -> 29.714286 | D29: =IFERROR((D24*D27)/'6. Assumptions'!$C$19,0) -> 52.761905 | E29: =IFERROR((E24*E27)/'6. Assumptions'!$C$19,0) -> 83.238095 | F29: =IFERROR((F24*F27)/'6. Assumptions'!$C$19,0) -> 25.809524
B31: Monthly contribution per customer | C31: =C24/C8 -> 156 | D31: =D24/D8 -> 277 | E31: =E24/E8 -> 437 | F31: =F24/F8 -> 271

Sheet 2. Vendor Pass-Through
B2: Vendor Pass-Through Reference Catalog
B3: Vendor invoices the client pays through HBC. Pass-through is REVENUE-NEUTRAL on HBC P&L (cost+0%). This sheet is reference only.
B5: Service | C5: Category | D5: Frequency | E5: Visits/yr | F5: Vendor cost / visit | G5: Annual vendor cost | H5: In Essentials? | I5: In Comfort? | J5: In Premier? | K5: Notes
B6: Lawn mowing 1/4 acre | C6: Recurring | D6: Weekly Apr-Oct | E6: 26 | F6: 45 | G6: =E6*F6 -> 1170 | H6: Y | I6: Y | J6: Y | K6: Standard residential mow
B7: Lawn fertilization treatment | C7: Recurring | D7: 5x/yr | E7: 5 | F7: 65 | G7: =E7*F7 -> 325 | H7: N | I7: Y | J7: Y | K7: TruGreen-tier sub program
B8: Snow plowing per push | C8: Recurring | D8: 20 events | E8: 20 | F8: 55 | G8: =E8*F8 -> 1100 | H8: Y | I8: Y | J8: Y | K8: Drive only, residential push
B9: Snow walkways shovel | C9: Recurring | D9: 20 events | E9: 20 | F9: 18 | G9: =E9*F9 -> 360 | H9: N | I9: Y | J9: Y | K9: Walks + steps add-on
B10: Gutter cleaning | C10: Recurring | D10: 2x/yr | E10: 2 | F10: 175 | G10: =E10*F10 -> 350 | H10: Y | I10: Y | J10: Y | K10: Spring + fall
B11: Pest perimeter treatment | C11: Recurring | D11: Quarterly | E11: 4 | F11: 95 | G11: =E11*F11 -> 380 | H11: Y | I11: Y | J11: Y | K11: Orkin/Terminix-tier
B12: HVAC filter replacement | C12: Recurring | D12: 4x/yr | E12: 4 | F12: 12 | G12: =E12*F12 -> 48 | H12: Y | I12: Y | J12: Y | K12: Filter cost only
B13: Leaf cleanup | C13: Seasonal | D13: 1x fall | E13: 1 | F13: 285 | G13: =E13*F13 -> 285 | H13: N | I13: Y | J13: Y | K13: Full bag and haul
B14: Mulching front beds | C14: Seasonal | D14: 1x spring | E14: 1 | F14: 425 | G14: =E14*F14 -> 425 | H14: N | I14: N | J14: Y | K14: 8 cu yd hardwood
B15: Shrub trimming | C15: Seasonal | D15: 2x/yr | E15: 2 | F15: 185 | G15: =E15*F15 -> 370 | H15: N | I15: N | J15: Y | K15: Foundation shrubs
B16: Sprinkler activation/blowout | C16: Seasonal | D16: 2x/yr | E16: 2 | F16: 95 | G16: =E16*F16 -> 190 | H16: N | I16: Y | J16: Y | K16: Spring + fall
B17: Sprinkler mid-season check | C17: Seasonal | D17: 1x | E17: 1 | F17: 85 | G17: =E17*F17 -> 85 | H17: N | I17: N | J17: Y | K17: Premier only
... B25: Annual home assessment | C25: Inspection | D25: 1x/yr | E25: 1 | F25: 0 | G25: =E25*F25 -> 0 | H25: Y | I25: Y | J25: Y | K25: Done by Adam, no vendor cost
B27: Total annual pass-through volume by tier | D27: Essentials | E27: =SUMIF(H6:H25,"Y",G6:G25) -> 3048
D28: Comfort | E28: =SUMIF(I6:I25,"Y",G6:G25) -> 5033
D29: Premier | E29: =SUMIF(J6:J25,"Y",G6:G25) -> 9200.5
B31: NOTE: This pass-through volume is what the CLIENT pays vendors through HBC, at exact cost.
B32: It does NOT flow into HBC's revenue or cost. HBC earns the management fee + add-on margin only.

Sheet 3. Scenario Analysis
B2: Scenario Analysis (year 1)
B3: Conservative / Base / Stretch business outcomes by year-1 customer count and tier mix.
B5: Metric | C5: Conservative | D5: Base | E5: Stretch | F5: Notes
B6: CUSTOMERS (year 1 ending)
B7: Total customers (end of yr 1) | C7: 30 | D7: 60 | E7: 100 | F7: Hudson + Bath + Montrose
B9: TIER MIX (% of customers)
B10: Essentials % | C10: 0.5 | D10: 0.4 | E10: 0.3
B11: Comfort % | C11: 0.3 | D11: 0.35 | E11: 0.35
B12: Premier % | C12: 0.15 | D12: 0.2 | E12: 0.25
B13: Snowbird % | C13: 0.05 | D13: 0.05 | E13: 0.1
B14: Mix total (must = 100%) | C14: =SUM(C10:C13) -> 1 | D14: =SUM(D10:D13) -> 1 | E14: =SUM(E10:E13) -> 1
B16: CUSTOMERS PER TIER
B17: Essentials customers | C17: =C7*C10 -> 15 | D17: =D7*D10 -> 24 | E17: =E7*E10 -> 30
B18: Comfort customers | C18: =C7*C11 -> 9 | D18: =D7*D11 -> 21 | E18: =E7*E11 -> 35
B19: Premier customers | C19: =C7*C12 -> 4.5 | D19: =D7*D12 -> 12 | E19: =E7*E12 -> 25
B20: Snowbird customers | C20: =C7*C13 -> 1.5 | D20: =D7*D13 -> 3 | E20: =E7*E13 -> 10
B22: ANNUAL HBC REVENUE
B23: Essentials revenue | C23: =C17*'1. Tier Economics'!$C$13 -> 38520 | D23: =D17*'1. Tier Economics'!$C$13 -> 61632 | E23: =E17*'1. Tier Economics'!$C$13 -> 77040
B24: Comfort revenue | C24: =C18*'1. Tier Economics'!$D$13 -> 41040 | D24: =D18*'1. Tier Economics'!$D$13 -> 95760 | E24: =E18*'1. Tier Economics'!$D$13 -> 159600
B25: Premier revenue | C25: =C19*'1. Tier Economics'!$E$13 -> 32400 | D25: =D19*'1. Tier Economics'!$E$13 -> 86400 | E25: =E19*'1. Tier Economics'!$E$13 -> 180000
B26: Snowbird revenue | C26: =C20*'1. Tier Economics'!$F$13 -> 3771 | D26: =D20*'1. Tier Economics'!$F$13 -> 7542 | E26: =E20*'1. Tier Economics'!$F$13 -> 25140
B27: TOTAL ANNUAL REVENUE | C27: =SUM(C23:C26) -> 115731 | D27: =SUM(D23:D26) -> 251334 | E27: =SUM(E23:E26) -> 441780
B29: ANNUAL CONTRIBUTION (revenue minus direct cost)
B30: Essentials contribution | C30: =C17*'1. Tier Economics'!$C$24 -> 28080 | D30: =D17*'1. Tier Economics'!$C$24 -> 44928 | E30: =E17*'1. Tier Economics'!$C$24 -> 56160
B31: Comfort contribution | C31: =C18*'1. Tier Economics'!$D$24 -> 29916 | D31: =D18*'1. Tier Economics'!$D$24 -> 69804 | E31: =E18*'1. Tier Economics'!$D$24 -> 116340
B32: Premier contribution | C32: =C19*'1. Tier Economics'!$E$24 -> 23598 | D32: =D19*'1. Tier Economics'!$E$24 -> 62928 | E32: =E19*'1. Tier Economics'!$E$24 -> 131100
B33: Snowbird contribution | C33: =C20*'1. Tier Economics'!$F$24 -> 2439 | D33: =D20*'1. Tier Economics'!$F$24 -> 4878 | E33: =E20*'1. Tier Economics'!$F$24 -> 16260
B34: Subtotal: contribution | C34: =SUM(C30:C33) -> 84033 | D34: =SUM(D30:D33) -> 182538 | E34: =SUM(E30:E33) -> 319860
B36: FIXED BUSINESS COSTS (annual)
B37: Less: Adam admin/sales overhead | C37: =-'6. Assumptions'!$C$12*12 -> -48000 | D37: =-'6. Assumptions'!$C$12*12 -> -48000 | E37: =-'6. Assumptions'!$C$12*12 -> -48000
B38: Less: CSM (if customer count >= trigger) | C38: =-IF(C7>='6. Assumptions'!$C$13,'6. Assumptions'!$C$14,0) -> 0 | D38: =-IF(D7>='6. Assumptions'!$C$13,'6. Assumptions'!$C$14,0) -> -45000 | E38: =-IF(E7>='6. Assumptions'!$C$13,'6. Assumptions'!$C$14,0) -> -45000
B39: Less: Marketing CAC (yr 1 cohort) | C39: =-C7*'6. Assumptions'!$C$19 -> -10500 | D39: =-D7*'6. Assumptions'!$C$19 -> -21000 | E39: =-E7*'6. Assumptions'!$C$19 -> -35000
B41: NET CONTRIBUTION (yr 1) | C41: =C34+C37+C38+C39 -> 25533 | D41: =D34+D37+D38+D39 -> 68538 | E41: =E34+E37+E38+E39 -> 191860
B42: Net margin % | C42: =IFERROR(C41/C27,0) -> 0.22062369 | D42: =IFERROR(D41/D27,0) -> 0.27269689 | E42: =IFERROR(E41/E27,0) -> 0.43428856
B44: Avg revenue/customer/yr | C44: =IFERROR(C27/C7,0) -> 3857.7 | D44: =IFERROR(D27/D7,0) -> 4188.9 | E44: =IFERROR(E27/E7,0) -> 4417.8
B45: Avg contribution/customer/yr | C45: =IFERROR(C34/C7,0) -> 2801.1 | D45: =IFERROR(D34/D7,0) -> 3042.3 | E45: =IFERROR(E34/E7,0) -> 3198.6

Sheet 4. Sensitivity
B2: Sensitivity Analysis
B3: How the Premier tier's annual contribution per customer responds to fee and Adam's hours.
B5: Premier annual contribution per customer at various fees / Adam coordination hours
B7: Adam hrs/yr \ Fee/mo | C7: 350 | D7: 400 | E7: 450 | F7: 500 | G7: 550 | H7: 600 | I7: 650 | J7: 700
B8: 10 | C8: =(C$7*12)+'1. Tier Economics'!$E$10-($B8*'1. Tier Economics'!$E$17)-'1. Tier Economics'!$E$19-'1. Tier Economics'!$E$20-'1. Tier Economics'!$E$21 -> 3594 | D8: =(D$7*12)+'1. Tier Economics'!$E$10-($B8*'1. Tier Economics'!$E$17)-'1. Tier Economics'!$E$19-'1. Tier Economics'!$E$20-'1. Tier Economics'!$E$21 -> 4194 | E8: =(E$7*12)+'1. Tier Economics'!$E$10-($B8*'1. Tier Economics'!$E$17)-'1. Tier Economics'!$E$19-'1. Tier Economics'!$E$20-'1. Tier Economics'!$E$21 -> 4794 | F8: =(F$7*12)+'1. Tier Economics'!$E$10-($B8*'1. Tier Economics'!$E$17)-'1. Tier Economics'!$E$19-'1. Tier Economics'!$E$20-'1. Tier Economics'!$E$21 -> 5394 | G8: =(G$7*12)+'1. Tier Economics'!$E$10-($B8*'1. Tier Economics'!$E$17)-'1. Tier Economics'!$E$19-'1. Tier Economics'!$E$20-'1. Tier Economics'!$E$21 -> 5994 | H8: =(H$7*12)+'1. Tier Economics'!$E$10-($B8*'1. Tier Economics'!$E$17)-'1. Tier Economics'!$E$19-'1. Tier Economics'!$E$20-'1. Tier Economics'!$E$21 -> 6594 | I8: =(I$7*12)+'1. Tier Economics'!$E$10-($B8*'1. Tier Economics'!$E$17)-'1. Tier Economics'!$E$19-'1. Tier Economics'!$E$20-'1. Tier Economics'!$E$21 -> 7194 | J8: =(J$7*12)+'1. Tier Economics'!$E$10-($B8*'1. Tier Economics'!$E$17)-'1. Tier Economics'!$E$19-'1. Tier Economics'!$E$20-'1. Tier Economics'!$E$21 -> 7794
B9: 14 | C9: =(C$7*12)+'1. Tier Economics'!$E$10-($B9*'1. Tier Economics'!$E$17)-'1. Tier Economics'!$E$19-'1. Tier Economics'!$E$20-'1. Tier Economics'!$E$21 -> 3294 | D9: =(D$7*12)+'1. Tier Economics'!$E$10-($B9*'1. Tier Economics'!$E$17)-'1. Tier Economics'!$E$19-'1. Tier Economics'!$E$20-'1. Tier Economics'!$E$21 -> 3894 | E9: =(E$7*12)+'1. Tier Economics'!$E$10-($B9*'1. Tier Economics'!$E$17)-'1. Tier Economics'!$E$19-'1. Tier Economics'!$E$20-'1. Tier Economics'!$E$21 -> 4494 | F9: =(F$7*12)+'1. Tier Economics'!$E$10-($B9*'1. Tier Economics'!$E$17)-'1. Tier Economics'!$E$19-'1. Tier Economics'!$E$20-'1. Tier Economics'!$E$21 -> 5094 | G9: =(G$7*12)+'1. Tier Economics'!$E$10-($B9*'1. Tier Economics'!$E$17)-'1. Tier Economics'!$E$19-'1. Tier Economics'!$E$20-'1. Tier Economics'!$E$21 -> 5694 | H9: =(H$7*12)+'1. Tier Economics'!$E$10-($B9*'1. Tier Economics'!$E$17)-'1. Tier Economics'!$E$19-'1. Tier Economics'!$E$20-'1. Tier Economics'!$E$21 -> 6294 | I9: =(I$7*12)+'1. Tier Economics'!$E$10-($B9*'1. Tier Economics'!$E$17)-'1. Tier Economics'!$E$19-'1. Tier Economics'!$E$20-'1. Tier Economics'!$E$21 -> 6894 | J9: =(J$7*12)+'1. Tier Economics'!$E$10-($B9*'1. Tier Economics'!$E$17)-'1. Tier Economics'!$E$19-'1. Tier Economics'!$E$20-'1. Tier Economics'!$E$21 -> 7494
B10: 18 | C10: =(C$7*12)+'1. Tier Economics'!$E$10-($B10*'1. Tier Economics'!$E$17)-'1. Tier Economics'!$E$19-'1. Tier Economics'!$E$20-'1. Tier Economics'!$E$21 -> 2994 | D10: =(D$7*12)+'1. Tier Economics'!$E$10-($B10*'1. Tier Economics'!$E$17)-'1. Tier Economics'!$E$19-'1. Tier Economics'!$E$20-'1. Tier Economics'!$E$21 -> 3594 | E10: =(E$7*12)+'1. Tier Economics'!$E$10-($B10*'1. Tier Economics'!$E$17)-'1. Tier Economics'!$E$19-'1. Tier Economics'!$E$20-'1. Tier Economics'!$E$21 -> 4194 | F10: =(F$7*12)+'1. Tier Economics'!$E$10-($B10*'1. Tier Economics'!$E$17)-'1. Tier Economics'!$E$19-'1. Tier Economics'!$E$20-'1. Tier Economics'!$E$21 -> 4794 | G10: =(G$7*12)+'1. Tier Economics'!$E$10-($B10*'1. Tier Economics'!$E$17)-'1. Tier Economics'!$E$19-'1. Tier Economics'!$E$20-'1. Tier Economics'!$E$21 -> 5394 | H10: =(H$7*12)+'1. Tier Economics'!$E$10-($B10*'1. Tier Economics'!$E$17)-'1. Tier Economics'!$E$19-'1. Tier Economics'!$E$20-'1. Tier Economics'!$E$21 -> 5994 | I10: =(I$7*12)+'1. Tier Economics'!$E$10-($B10*'1. Tier Economics'!$E$17)-'1. Tier Economics'!$E$19-'1. Tier Economics'!$E$20-'1. Tier Economics'!$E$21 -> 6594 | J10: =(J$7*12)+'1. Tier Economics'!$E$10-($B10*'1. Tier Economics'!$E$17)-'1. Tier Economics'!$E$19-'1. Tier Economics'!$E$20-'1. Tier Economics'!$E$21 -> 7194
B11: 22 | C11: =(C$7*12)+'1. Tier Economics'!$E$10-($B11*'1. Tier Economics'!$E$17)-'1. Tier Economics'!$E$19-'1. Tier Economics'!$E$20-'1. Tier Economics'!$E$21 -> 2694 | D11: =(D$7*12)+'1. Tier Economics'!$E$10-($B11*'1. Tier Economics'!$E$17)-'1. Tier Economics'!$E$19-'1. Tier Economics'!$E$20-'1. Tier Economics'!$E$21 -> 3294 | E11: =(E$7*12)+'1. Tier Economics'!$E$10-($B11*'1. Tier Economics'!$E$17)-'1. Tier Economics'!$E$19-'1. Tier Economics'!$E$20-'1. Tier Economics'!$E$21 -> 3894 | F11: =(F$7*12)+'1. Tier Economics'!$E$10-($B11*'1. Tier Economics'!$E$17)-'1. Tier Economics'!$E$19-'1. Tier Economics'!$E$20-'1. Tier Economics'!$E$21 -> 4494 | G11: =(G$7*12)+'1. Tier Economics'!$E$10-($B11*'1. Tier Economics'!$E$17)-'1. Tier Economics'!$E$19-'1. Tier Economics'!$E$20-'1. Tier Economics'!$E$21 -> 5094 | H11: =(H$7*12)+'1. Tier Economics'!$E$10-($B11*'1. Tier Economics'!$E$17)-'1. Tier Economics'!$E$19-'1. Tier Economics'!$E$20-'1. Tier Economics'!$E$21 -> 5694 | I11: =(I$7*12)+'1. Tier Economics'!$E$10-($B11*'1. Tier Economics'!$E$17)-'1. Tier Economics'!$E$19-'1. Tier Economics'!$E$20-'1. Tier Economics'!$E$21 -> 6294 | J11: =(J$7*12)+'1. Tier Economics'!$E$10-($B11*'1. Tier Economics'!$E$17)-'1. Tier Economics'!$E$19-'1. Tier Economics'!$E$20-'1. Tier Economics'!$E$21 -> 6894
B12: 26 | C12: =(C$7*12)+'1. Tier Economics'!$E$10-($B12*'1. Tier Economics'!$E$17)-'1. Tier Economics'!$E$19-'1. Tier Economics'!$E$20-'1. Tier Economics'!$E$21 -> 2394 | D12: =(D$7*12)+'1. Tier Economics'!$E$10-($B12*'1. Tier Economics'!$E$17)-'1. Tier Economics'!$E$19-'1. Tier Economics'!$E$20-'1. Tier Economics'!$E$21 -> 2994 | E12: =(E$7*12)+'1. Tier Economics'!$E$10-($B12*'1. Tier Economics'!$E$17)-'1. Tier Economics'!$E$19-'1. Tier Economics'!$E$20-'1. Tier Economics'!$E$21 -> 3594 | F12: =(F$7*12)+'1. Tier Economics'!$E$10-($B12*'1. Tier Economics'!$E$17)-'1. Tier Economics'!$E$19-'1. Tier Economics'!$E$20-'1. Tier Economics'!$E$21 -> 4194 | G12: =(G$7*12)+'1. Tier Economics'!$E$10-($B12*'1. Tier Economics'!$E$17)-'1. Tier Economics'!$E$19-'1. Tier Economics'!$E$20-'1. Tier Economics'!$E$21 -> 4794 | H12: =(H$7*12)+'1. Tier Economics'!$E$10-($B12*'1. Tier Economics'!$E$17)-'1. Tier Economics'!$E$19-'1. Tier Economics'!$E$20-'1. Tier Economics'!$E$21 -> 5394 | I12: =(I$7*12)+'1. Tier Economics'!$E$10-($B12*'1. Tier Economics'!$E$17)-'1. Tier Economics'!$E$19-'1. Tier Economics'!$E$20-'1. Tier Economics'!$E$21 -> 5994 | J12: =(J$7*12)+'1. Tier Economics'!$E$10-($B12*'1. Tier Economics'!$E$17)-'1. Tier Economics'!$E$19-'1. Tier Economics'!$E$20-'1. Tier Economics'!$E$21 -> 6594
B13: 30 | C13: =(C$7*12)+'1. Tier Economics'!$E$10-($B13*'1. Tier Economics'!$E$17)-'1. Tier Economics'!$E$19-'1. Tier Economics'!$E$20-'1. Tier Economics'!$E$21 -> 2094 | D13: =(D$7*12)+'1. Tier Economics'!$E$10-($B13*'1. Tier Economics'!$E$17)-'1. Tier Economics'!$E$19-'1. Tier Economics'!$E$20-'1. Tier Economics'!$E$21 -> 2694 | E13: =(E$7*12)+'1. Tier Economics'!$E$10-($B13*'1. Tier Economics'!$E$17)-'1. Tier Economics'!$E$19-'1. Tier Economics'!$E$20-'1. Tier Economics'!$E$21 -> 3294 | F13: =(F$7*12)+'1. Tier Economics'!$E$10-($B13*'1. Tier Economics'!$E$17)-'1. Tier Economics'!$E$19-'1. Tier Economics'!$E$20-'1. Tier Economics'!$E$21 -> 3894 | G13: =(G$7*12)+'1. Tier Economics'!$E$10-($B13*'1. Tier Economics'!$E$17)-'1. Tier Economics'!$E$19-'1. Tier Economics'!$E$20-'1. Tier Economics'!$E$21 -> 4494 | H13: =(H$7*12)+'1. Tier Economics'!$E$10-($B13*'1. Tier Economics'!$E$17)-'1. Tier Economics'!$E$19-'1. Tier Economics'!$E$20-'1. Tier Economics'!$E$21 -> 5094 | I13: =(I$7*12)+'1. Tier Economics'!$E$10-($B13*'1. Tier Economics'!$E$17)-'1. Tier Economics'!$E$19-'1. Tier Economics'!$E$20-'1. Tier Economics'!$E$21 -> 5694 | J13: =(J$7*12)+'1. Tier Economics'!$E$10-($B13*'1. Tier Economics'!$E$17)-'1. Tier Economics'!$E$19-'1. Tier Economics'!$E$20-'1. Tier Economics'!$E$21 -> 6294
B14: 36 | C14: =(C$7*12)+'1. Tier Economics'!$E$10-($B14*'1. Tier Economics'!$E$17)-'1. Tier Economics'!$E$19-'1. Tier Economics'!$E$20-'1. Tier Economics'!$E$21 -> 1644 | D14: =(D$7*12)+'1. Tier Economics'!$E$10-($B14*'1. Tier Economics'!$E$17)-'1. Tier Economics'!$E$19-'1. Tier Economics'!$E$20-'1. Tier Economics'!$E$21 -> 2244 | E14: =(E$7*12)+'1. Tier Economics'!$E$10-($B14*'1. Tier Economics'!$E$17)-'1. Tier Economics'!$E$19-'1. Tier Economics'!$E$20-'1. Tier Economics'!$E$21 -> 2844 | F14: =(F$7*12)+'1. Tier Economics'!$E$10-($B14*'1. Tier Economics'!$E$17)-'1. Tier Economics'!$E$19-'1. Tier Economics'!$E$20-'1. Tier Economics'!$E$21 -> 3444 | G14: =(G$7*12)+'1. Tier Economics'!$E$10-($B14*'1. Tier Economics'!$E$17)-'1. Tier Economics'!$E$19-'1. Tier Economics'!$E$20-'1. Tier Economics'!$E$21 -> 4044 | H14: =(H$7*12)+'1. Tier Economics'!$E$10-($B14*'1. Tier Economics'!$E$17)-'1. Tier Economics'!$E$19-'1. Tier Economics'!$E$20-'1. Tier Economics'!$E$21 -> 4644 | I14: =(I$7*12)+'1. Tier Economics'!$E$10-($B14*'1. Tier Economics'!$E$17)-'1. Tier Economics'!$E$19-'1. Tier Economics'!$E$20-'1. Tier Economics'!$E$21 -> 5244 | J14: =(J$7*12)+'1. Tier Economics'!$E$10-($B14*'1. Tier Economics'!$E$17)-'1. Tier Economics'!$E$19-'1. Tier Economics'!$E$20-'1. Tier Economics'!$E$21 -> 5844
B15: 42 | C15: =(C$7*12)+'1. Tier Economics'!$E$10-($B15*'1. Tier Economics'!$E$17)-'1. Tier Economics'!$E$19-'1. Tier Economics'!$E$20-'1. Tier Economics'!$E$21 -> 1194 | D15: =(D$7*12)+'1. Tier Economics'!$E$10-($B15*'1. Tier Economics'!$E$17)-'1. Tier Economics'!$E$19-'1. Tier Economics'!$E$20-'1. Tier Economics'!$E$21 -> 1794 | E15: =(E$7*12)+'1. Tier Economics'!$E$10-($B15*'1. Tier Economics'!$E$17)-'1. Tier Economics'!$E$19-'1. Tier Economics'!$E$20-'1. Tier Economics'!$E$21 -> 2394 | F15: =(F$7*12)+'1. Tier Economics'!$E$10-($B15*'1. Tier Economics'!$E$17)-'1. Tier Economics'!$E$19-'1. Tier Economics'!$E$20-'1. Tier Economics'!$E$21 -> 2994 | G15: =(G$7*12)+'1. Tier Economics'!$E$10-($B15*'1. Tier Economics'!$E$17)-'1. Tier Economics'!$E$19-'1. Tier Economics'!$E$20-'1. Tier Economics'!$E$21 -> 3594 | H15: =(H$7*12)+'1. Tier Economics'!$E$10-($B15*'1. Tier Economics'!$E$17)-'1. Tier Economics'!$E$19-'1. Tier Economics'!$E$20-'1. Tier Economics'!$E$21 -> 4194 | I15: =(I$7*12)+'1. Tier Economics'!$E$10-($B15*'1. Tier Economics'!$E$17)-'1. Tier Economics'!$E$19-'1. Tier Economics'!$E$20-'1. Tier Economics'!$E$21 -> 4794 | J15: =(J$7*12)+'1. Tier Economics'!$E$10-($B15*'1. Tier Economics'!$E$17)-'1. Tier Economics'!$E$19-'1. Tier Economics'!$E$20-'1. Tier Economics'!$E$21 -> 5394
B18: Premier LTV : CAC at varying churn and CAC
B20: Churn % \ CAC | C20: 200 | D20: 300 | E20: 400 | F20: 500 | G20: 600 | H20: 750 | I20: 1000 | J20: 1500
B21: 0.1 | C21: =('1. Tier Economics'!$E$24/$B21)/C$20 -> 262.2 | D21: =('1. Tier Economics'!$E$24/$B21)/D$20 -> 174.8 | E21: =('1. Tier Economics'!$E$24/$B21)/E$20 -> 131.1 | F21: =('1. Tier Economics'!$E$24/$B21)/F$20 -> 104.88 | G21: =('1. Tier Economics'!$E$24/$B21)/G$20 -> 87.4 | H21: =('1. Tier Economics'!$E$24/$B21)/H$20 -> 69.92 | I21: =('1. Tier Economics'!$E$24/$B21)/I$20 -> 52.44 | J21: =('1. Tier Economics'!$E$24/$B21)/J$20 -> 34.96
B22: 0.12 | C22: =('1. Tier Economics'!$E$24/$B22)/C$20 -> 218.5 | D22: =('1. Tier Economics'!$E$24/$B22)/D$20 -> 145.66667 | E22: =('1. Tier Economics'!$E$24/$B22)/E$20 -> 109.25 | F22: =('1. Tier Economics'!$E$24/$B22)/F$20 -> 87.4 | G22: =('1. Tier Economics'!$E$24/$B22)/G$20 -> 72.833333 | H22: =('1. Tier Economics'!$E$24/$B22)/H$20 -> 58.266667 | I22: =('1. Tier Economics'!$E$24/$B22)/I$20 -> 43.7 | J22: =('1. Tier Economics'!$E$24/$B22)/J$20 -> 29.133333
B23: 0.15 | C23: =('1. Tier Economics'!$E$24/$B23)/C$20 -> 174.8 | D23: =('1. Tier Economics'!$E$24/$B23)/D$20 -> 116.53333 | E23: =('1. Tier Economics'!$E$24/$B23)/E$20 -> 87.4 | F23: =('1. Tier Economics'!$E$24/$B23)/F$20 -> 69.92 | G23: =('1. Tier Economics'!$E$24/$B23)/G$20 -> 58.266667 | H23: =('1. Tier Economics'!$E$24/$B23)/H$20 -> 46.613333 | I23: =('1. Tier Economics'!$E$24/$B23)/I$20 -> 34.96 | J23: =('1. Tier Economics'!$E$24/$B23)/J$20 -> 23.306667
B24: 0.18 | C24: =('1. Tier Economics'!$E$24/$B24)/C$20 -> 145.66667 | D24: =('1. Tier Economics'!$E$24/$B24)/D$20 -> 97.111111 | E24: =('1. Tier Economics'!$E$24/$B24)/E$20 -> 72.833333 | F24: =('1. Tier Economics'!$E$24/$B24)/F$20 -> 58.266667 | G24: =('1. Tier Economics'!$E$24/$B24)/G$20 -> 48.555556 | H24: =('1. Tier Economics'!$E$24/$B24)/H$20 -> 38.844444 | I24: =('1. Tier Economics'!$E$24/$B24)/I$20 -> 29.133333 | J24: =('1. Tier Economics'!$E$24/$B24)/J$20 -> 19.422222
B25: 0.22 | C25: =('1. Tier Economics'!$E$24/$B25)/C$20 -> 119.18182 | D25: =('1. Tier Economics'!$E$24/$B25)/D$20 -> 79.454545 | E25: =('1. Tier Economics'!$E$24/$B25)/E$20 -> 59.590909 | F25: =('1. Tier Economics'!$E$24/$B25)/F$20 -> 47.672727 | G25: =('1. Tier Economics'!$E$24/$B25)/G$20 -> 39.727273 | H25: =('1. Tier Economics'!$E$24/$B25)/H$20 -> 31.781818 | I25: =('1. Tier Economics'!$E$24/$B25)/I$20 -> 23.836364 | J25: =('1. Tier Economics'!$E$24/$B25)/J$20 -> 15.890909
B26: 0.25 | C26: =('1. Tier Economics'!$E$24/$B26)/C$20 -> 104.88 | D26: =('1. Tier Economics'!$E$24/$B26)/D$20 -> 69.92 | E26: =('1. Tier Economics'!$E$24/$B26)/E$20 -> 52.44 | F26: =('1. Tier Economics'!$E$24/$B26)/F$20 -> 41.952 | G26: =('1. Tier Economics'!$E$24/$B26)/G$20 -> 34.96 | H26: =('1. Tier Economics'!$E$24/$B26)/H$20 -> 27.968 | I26: =('1. Tier Economics'!$E$24/$B26)/I$20 -> 20.976 | J26: =('1. Tier Economics'!$E$24/$B26)/J$20 -> 13.984
B27: 0.3 | C27: =('1. Tier Economics'!$E$24/$B27)/C$20 -> 87.4 | D27: =('1. Tier Economics'!$E$24/$B27)/D$20 -> 58.266667 | E27: =('1. Tier Economics'!$E$24/$B27)/E$20 -> 43.7 | F27: =('1. Tier Economics'!$E$24/$B27)/F$20 -> 34.96 | G27: =('1. Tier Economics'!$E$24/$B27)/G$20 -> 29.133333 | H27: =('1. Tier Economics'!$E$24/$B27)/H$20 -> 23.306667 | I27: =('1. Tier Economics'!$E$24/$B27)/I$20 -> 17.48 | J27: =('1. Tier Economics'!$E$24/$B27)/J$20 -> 11.653333
B30: GUIDE
B31: Healthy SaaS-like LTV:CAC = 3x or higher. Below 1x = unprofitable.
B32: Top table green = strong per-customer contribution; red = underwater on direct cost.

Sheet 5. 36-Month Forecast
B2: 36-Month Forecast (Base Scenario)
B3: Customer growth, revenue, and contribution. CSM auto-adds when customer count crosses trigger.
B5: Month | C5: M1 | D5: M2 | E5: M3 | F5: M4 | G5: M5 | H5: M6 | I5: M7 | J5: M8 | K5: M9 | L5: M10 | M5: M11 | N5: M12 | O5: M13 | P5: M14 | Q5: M15 | R5: M16 | S5: M17 | T5: M18 | U5: M19 | V5: M20 | W5: M21 | X5: M22 | Y5: M23 | Z5: M24 | AA5: M25 | AB5: M26 | AC5: M27 | AD5: M28 | AE5: M29 | AF5: M30 | AG5: M31 | AH5: M32 | AI5: M33 | AJ5: M34 | AK5: M35 | AL5: M36
B7: New customers added | C7: 2 | D7: 3 | E7: 3 | F7: 4 | G7: 4 | H7: 5 | I7: 5 | J7: 5 | K7: 6 | L7: 6 | M7: 6 | N7: 6 | O7: 6 | P7: 6 | Q7: 7 | R7: 7 | S7: 7 | T7: 7 | U7: 8 | V7: 8 | W7: 8 | X7: 8 | Y7: 8 | Z7: 8 | AA7: 8 | AB7: 8 | AC7: 8 | AD7: 9 | AE7: 9 | AF7: 9 | AG7: 9 | AH7: 9 | AI7: 9 | AJ7: 10 | AK7: 10 | AL7: 10
B8: Churned customers (calc) | C8: 0 | D8: =ROUND(C10*('6. Assumptions'!$C$20/12),1) -> 0 | E8: =ROUND(D10*('6. Assumptions'!$C$20/12),1) -> 0.1 | F8: =ROUND(E10*('6. Assumptions'!$C$20/12),1) -> 0.1 | G8: =ROUND(F10*('6. Assumptions'!$C$20/12),1) -> 0.2 | H8: =ROUND(G10*('6. Assumptions'!$C$20/12),1) -> 0.2 | I8: =ROUND(H10*('6. Assumptions'!$C$20/12),1) -> 0.3 | J8: =ROUND(I10*('6. Assumptions'!$C$20/12),1) -> 0.4 | K8: =ROUND(J10*('6. Assumptions'!$C$20/12),1) -> 0.4 | ... AL8: =ROUND(AK10*('6. Assumptions'!$C$20/12),1) -> 3
B10: Active customers (end of month) | C10: =C7-C8 -> 2 | D10: =C10+D7-D8 -> 5 | E10: =D10+E7-E8 -> 7.9 | F10: =E10+F7-F8 -> 11.8 | G10: =F10+G7-G8 -> 15.6 | H10: =G10+H7-H8 -> 20.4 | I10: =H10+I7-I8 -> 25.1 | J10: =I10+J7-J8 -> 29.7 | K10: =J10+K7-K8 -> 35.3 | ... AL10: =AK10+AL7-AL8 -> 203.8
B12: Blended monthly fee + add-ons /cust | C12: 362 | D12: 362 | E12: 362 | F12: 362 | G12: 362 | H12: 362 | I12: 362 | J12: 362 | K12: 362 | L12: 362 | M12: 362 | N12: 362 | O12: 362 | P12: 362 | Q12: 362 | R12: 362 | S12: 362 | T12: 362 | U12: 362 | V12: 362 | W12: 362 | X12: 362 | Y12: 362 | Z12: 362 | AA12: 362 | AB12: 362 | AC12: 362 | AD12: 362 | AE12: 362 | AF12: 362 | AG12: 362 | AH12: 362 | AI12: 362 | AJ12: 362 | AK12: 362 | AL12: 362
B13: Monthly HBC revenue | C13: =C10*C12 -> 724 | D13: =D10*D12 -> 1810 | E13: =E10*E12 -> 2859.8 | F13: =F10*F12 -> 4271.6 | G13: =G10*G12 -> 5647.2 | H13: =H10*H12 -> 7384.8 | I13: =I10*I12 -> 9086.2 | J13: =J10*J12 -> 10751.4 | ... AL13: =AL10*AL12 -> 73775.6
B14: Avg coord hrs/cust/mo | C14: 1 | D14: 1 | E14: 1 | F14: 1 | G14: 1 | H14: 1 | I14: 1 | J14: 1 | K14: 1 | L14: 1 | M14: 1 | N14: 1 | O14: 1 | P14: 1 | Q14: 1 | R14: 1 | S14: 1 | T14: 1 | U14: 1 | V14: 1 | W14: 1 | X14: 1 | Y14: 1 | Z14: 1 | AA14: 1 | AB14: 1 | AC14: 1 | AD14: 1 | AE14: 1 | AF14: 1 | AG14: 1 | AH14: 1 | AI14: 1 | AJ14: 1 | AK14: 1 | AL14: 1
B15: Direct cost / customer / mo | C15: =(C14*'1. Tier Economics'!$C$17)+'6. Assumptions'!$C$16+'6. Assumptions'!$C$17 -> 88 | D15: =(D14*'1. Tier Economics'!$C$17)+'6. Assumptions'!$C$16+'6. Assumptions'!$C$17 -> 88 | E15: =(E14*'1. Tier Economics'!$C$17)+'6. Assumptions'!$C$16+'6. Assumptions'!$C$17 -> 88 | F15: =(F14*'1. Tier Economics'!$C$17)+'6. Assumptions'!$C$16+'6. Assumptions'!$C$17 -> 88 | G15: =(G14*'1. Tier Economics'!$C$17)+'6. Assumptions'!$C$16+'6. Assumptions'!$C$17 -> 88 | H15: =(H14*'1. Tier Economics'!$C$17)+'6. Assumptions'!$C$16+'6. Assumptions'!$C$17 -> 88 | I15: =(I14*'1. Tier Economics'!$C$17)+'6. Assumptions'!$C$16+'6. Assumptions'!$C$17 -> 88 | J15: =(J14*'1. Tier Economics'!$C$17)+'6. Assumptions'!$C$16+'6. Assumptions'!$C$17 -> 88 | ... AL15: =(AL14*'1. Tier Economics'!$C$17)+'6. Assumptions'!$C$16+'6. Assumptions'!$C$17 -> 88
B16: Total monthly direct cost | C16: =C10*C15 -> 176 | D16: =D10*D15 -> 440 | E16: =E10*E15 -> 695.2 | F16: =F10*F15 -> 1038.4 | G16: =G10*G15 -> 1372.8 | H16: =H10*H15 -> 1795.2 | I16: =I10*I15 -> 2208.8 | J16: =J10*J15 -> 2613.6 | ... AL16: =AL10*AL15 -> 17934.4
B17: Adam admin + CSM (fixed monthly) | C17: ='6. Assumptions'!$C$12+IF(C10>='6. Assumptions'!$C$13,'6. Assumptions'!$C$14/12,0) -> 4000 | D17: ='6. Assumptions'!$C$12+IF(D10>='6. Assumptions'!$C$13,'6. Assumptions'!$C$14/12,0) -> 4000 | E17: ='6. Assumptions'!$C$12+IF(E10>='6. Assumptions'!$C$13,'6. Assumptions'!$C$14/12,0) -> 4000 | F17: ='6. Assumptions'!$C$12+IF(F10>='6. Assumptions'!$C$13,'6. Assumptions'!$C$14/12,0) -> 4000 | G17: ='6. Assumptions'!$C$12+IF(G10>='6. Assumptions'!$C$13,'6. Assumptions'!$C$14/12,0) -> 4000 | H17: ='6. Assumptions'!$C$12+IF(H10>='6. Assumptions'!$C$13,'6. Assumptions'!$C$14/12,0) -> 4000 | I17: ='6. Assumptions'!$C$12+IF(I10>='6. Assumptions'!$C$13,'6. Assumptions'!$C$14/12,0) -> 4000 | J17: ='6. Assumptions'!$C$12+IF(J10>='6. Assumptions'!$C$13,'6. Assumptions'!$C$14/12,0) -> 4000 | ... AL17: ='6. Assumptions'!$C$12+IF(AL10>='6. Assumptions'!$C$13,'6. Assumptions'!$C$14/12,0) -> 7750
B18: Marketing spend (CAC * new) | C18: =C7*'6. Assumptions'!$C$19 -> 700 | D18: =D7*'6. Assumptions'!$C$19 -> 1050 | E18: =E7*'6. Assumptions'!$C$19 -> 1050 | F18: =F7*'6. Assumptions'!$C$19 -> 1400 | G18: =G7*'6. Assumptions'!$C$19 -> 1400 | H18: =H7*'6. Assumptions'!$C$19 -> 1750 | I18: =I7*'6. Assumptions'!$C$19 -> 1750 | J18: =J7*'6. Assumptions'!$C$19 -> 1750 | ... AL18: =AL7*'6. Assumptions'!$C$19 -> 3500
B20: MONTHLY NET CONTRIBUTION | C20: =C13-C16-C17-C18 -> -4152 | D20: =D13-D16-D17-D18 -> -3680 | E20: =E13-E16-E17-E18 -> -2885.4 | F20: =F13-F16-F17-F18 -> -2166.8 | G20: =G13-G16-G17-G18 -> -1125.6 | H20: =H13-H16-H17-H18 -> -160.4 | I20: =I13-I16-I17-I18 -> 1127.4 | J20: =J13-J16-J17-J18 -> 2387.8 | ... AL20: =AL13-AL16-AL17-AL18 -> 44591.2
B21: Cumulative net contribution | C21: =C20 -> -4152 | D21: =C21+D20 -> -7832 | E21: =D21+E20 -> -10717.4 | F21: =E21+F20 -> -12884.2 | G21: =F21+G20 -> -14009.8 | H21: =G21+H20 -> -14170.2 | I21: =H21+I20 -> -13042.8 | J21: =I21+J20 -> -10655 | K21: =J21+K20 -> -7082.8 | ... AL21: =AK21+AL20 -> 595862
B24: YEAR-END SUMMARY
B25: Year 1 ending customers | C25: =N10 -> 51.5
B26: Year 2 ending customers | C26: =Z10 -> 124.3
B27: Year 3 ending customers | C27: =AL10 -> 203.8
B29: Year 1 net contribution | C29: =SUM(C20:N20) -> 8816.2
B30: Year 2 net contribution | C30: =SUM(O20:Z20) -> 171161
B31: Year 3 net contribution | C31: =SUM(AA20:AL20) -> 415884.8
B33: 3-year cumulative contribution | C33: =AL21 -> 595862

Sheet 6. Assumptions
B2: HBC Concierge — Assumptions
B3: Management-fee model. Vendor invoices pass through at cost (cost + 0%). Edit any blue cell.
B5: MANAGEMENT FEE PRICING (monthly, $)
B6: Essentials fee/mo | C6: 199 | D6: Entry tier
B7: Comfort fee/mo | C7: 350 | D7: Mid tier
B8: Premier fee/mo | C8: 550 | D8: Top tier
B9: Snowbird fee/mo (6-mo Nov-Apr) | C9: 399 | D9: Seasonal commit
B11: OPERATING COST INPUTS
B12: Adam time allocation $/mo (year 1) | C12: 4000 | D12: Lean launch: Adam handles all coordination
B13: CSM hired at customer count = | C13: 50 | D13: Trigger to bring on first part-time CSM
B14: CSM annual loaded cost | C14: 45000 | D14: Part-time concierge mgr w/ benefits
B15: Customers per CSM (max) | C15: 100 | D15: Manageable book of business per CSM
B16: Software/portal cost/customer/mo | C16: 8 | D16: CRM, client portal, scheduling, payments
B17: Insurance + bond /customer/mo | C17: 5 | D17: Liability allocation per active customer
B18: Vendor management fee on pass-through | C18: 0 | D18: 0% = pure pass-through (no vendor markup)
B19: Marketing CAC (target) | C19: 350 | D19: Cost per acquired customer
B20: Annual customer churn rate | C20: 0.18 | D20: Conservative year-1 estimate
B21: Avg add-on / referral rev /cust /mo | C21: 50 | D21: Premium upsells, project management fees
B22: Add-on margin % | C22: 0.5 | D22: Margin on add-ons / project mgmt fees
